pysonnet/__init__.py
pysonnet/__main__.py
pysonnet/ast.py
pysonnet/cli.py
pysonnet/errors.py
pysonnet/evaluator.py
pysonnet/lexer.py
pysonnet/objects.py
pysonnet/parser.py
pysonnet/py.typed
pysonnet/stdlib.py
pysonnet/token.py
pysonnet/types.py
pysonnet-0.0.2.dist-info/LICENSE
pysonnet-0.0.2.dist-info/METADATA
pysonnet-0.0.2.dist-info/WHEEL
pysonnet-0.0.2.dist-info/entry_points.txt
pysonnet-0.0.2.dist-info/RECORD
