Metadata-Version: 2.1
Name: pysonnet
Version: 0.0.2
Summary: 📜 A pure Python implementation of the Jsonnet language
Home-page: https://github.com/altescy/pysonnet
License: MIT
Author: altescy
Author-email: altescy@fastmail.com
Requires-Python: >=3.8,<4.0
Classifier: License :: OSI Approved :: MIT License
Classifier: Programming Language :: Python :: 3
Classifier: Programming Language :: Python :: 3.8
Classifier: Programming Language :: Python :: 3.9
Classifier: Programming Language :: Python :: 3.10
Classifier: Programming Language :: Python :: 3.11
Classifier: Programming Language :: Python :: 3.12
